ckanext/__init__.py
ckanext/fdt_sqlalchemy/__init__.py
ckanext/fdt_sqlalchemy/plugin.py
ckanext/fdt_sqlalchemy/tests/__init__.py
ckanext/fdt_sqlalchemy/tests/test_plugin.py
ckanext_fdt_sqlalchemy-0.0.2.post1.dist-info/LICENSE
ckanext_fdt_sqlalchemy-0.0.2.post1.dist-info/METADATA
ckanext_fdt_sqlalchemy-0.0.2.post1.dist-info/WHEEL
ckanext_fdt_sqlalchemy-0.0.2.post1.dist-info/entry_points.txt
ckanext_fdt_sqlalchemy-0.0.2.post1.dist-info/top_level.txt
ckanext_fdt_sqlalchemy-0.0.2.post1.dist-info/RECORD
