Metadata-Version: 2.1
Name: ckanext-fdt-sqlalchemy
Version: 0.0.2.post1
Summary: Enable SQLAlchemy pane of Flask-DebugToolbar
Author-email: DataShades <datashades@linkdigital.com.au>, Sergey Motornyuk <sergey.motornyuk@linkdigital.com.au>
Maintainer-email: DataShades <datashades@linkdigital.com.au>
License: AGPL
Project-URL: Homepage, https://github.com/ckan/ckanext-fdt-sqlalchemy
Keywords: CKAN SQL debug
Classifier: Development Status :: 4 - Beta
Classifier: License :: OSI Approved :: GNU Affero General Public License v3 or later (AGPLv3+)
Classifier: Programming Language :: Python :: 3.8
Classifier: Programming Language :: Python :: 3.9
Classifier: Programming Language :: Python :: 3.10
License-File: LICENSE
Provides-Extra: deps
Requires-Dist: flask-sqlalchemy ~=2.5 ; extra == 'deps'
Provides-Extra: dev
Requires-Dist: flask-sqlalchemy ~=2.5 ; extra == 'dev'
Requires-Dist: pytest-ckan ; extra == 'dev'
Provides-Extra: test
Requires-Dist: pytest-ckan ; extra == 'test'
